LICENSE.txt
MANIFEST.in
README.rst
requirements.txt
setup.cfg
setup.py
test_requirements.txt
pyconsensus/__init__.py
pyconsensus/plotj.py
pyconsensus.egg-info/PKG-INFO
pyconsensus.egg-info/SOURCES.txt
pyconsensus.egg-info/dependency_links.txt
pyconsensus.egg-info/requires.txt
pyconsensus.egg-info/top_level.txt
test/test_consensus.py