Metadata-Version: 1.1
Name: pyconsensus
Version: 0.5.8
Summary: Standalone implementation of Augur's consensus mechanism
Home-page: https://github.com/AugurProject/pyconsensus
Author: Jack Peterson
Author-email: <jack@tinybike.net>
License: GPL
Download-URL: https://github.com/AugurProject/pyconsensus/tarball/0.5.8
Keywords: consensus,prediction market,PM,truthcoin,augur,oracle
Platform: UNKNOWN
